digcommpy/__init__.py
digcommpy/channels.py
digcommpy/checks.py
digcommpy/decoders.py
digcommpy/demodulators.py
digcommpy/encoders.py
digcommpy/information_theory.py
digcommpy/messages.py
digcommpy/metrics.py
digcommpy/modulators.py
digcommpy/parsers.py
digcommpy/simulations.py
digcommpy-0.9.dist-info/LICENSE
digcommpy-0.9.dist-info/METADATA
digcommpy-0.9.dist-info/WHEEL
digcommpy-0.9.dist-info/top_level.txt
digcommpy-0.9.dist-info/RECORD
