Metadata-Version: 2.1
Name: digcommpy
Version: 0.9
Summary: Package for digitial communications functions
Home-page: https://gitlab.com/klb2/digcommpy
Author: Karl Besser
Author-email: karl-ludwig.besser@tu-dresden.de
License: BSD
Project-URL: Documentation, https://digcommpy.readthedocs.io/
Project-URL: Source Code, https://gitlab.com/klb2/digcommpy
Platform: UNKNOWN
License-File: LICENSE
Requires-Dist: numpy
Requires-Dist: scipy
Requires-Dist: joblib
Requires-Dist: pandas
